{
  "parcel": {
    "parcel_id": "0023H00275000000",
    "address": "67 FOUNTAIN ST",
    "city": "Ward 25",
    "zip_code": "15212",
    "county": "Allegheny",
    "current_owner_name": "67   FOUNTAIN ST",
    "current_mailing_address": "67   FOUNTAIN ST",
    "current_ownership_type": "REGULAR",
    "land_use_code": null,
    "land_use_description": "SINGLE FAMILY",
    "acreage": 0.078,
    "latitude": 40.41752,
    "longitude": -80.0636
  },
  "assessments": {
    "parcel_id": "0023H00275000000",
    "assessments": [
      {
        "tax_year": 2026,
        "assessed_value": 42700,
        "market_value": 42700,
        "land_value": 25300,
        "improvement_value": 17400,
        "land_value_percentage": 59.3,
        "improvement_value_percentage": 40.7,
        "market_to_assessed_ratio": 1.0,
        "assessed_value_change": 1902,
        "assessed_value_change_pct": 4.66,
        "total_exemption_amount": 0,
        "net_assessed_value": 42700,
        "assessment_date": "2026-01-15"
      },
      {
        "tax_year": 2025,
        "assessed_value": 40798,
        "market_value": 40798,
        "land_value": 24173,
        "improvement_value": 16625,
        "land_value_percentage": 59.3,
        "improvement_value_percentage": 40.7,
        "market_to_assessed_ratio": 1.0,
        "assessed_value_change": 0,
        "assessed_value_change_pct": 0.0,
        "total_exemption_amount": 0,
        "net_assessed_value": 40798,
        "assessment_date": "2025-01-15"
      },
      {
        "tax_year": 2024,
        "assessed_value": 40798,
        "market_value": 40798,
        "land_value": 24173,
        "improvement_value": 16625,
        "land_value_percentage": 59.3,
        "improvement_value_percentage": 40.7,
        "market_to_assessed_ratio": 1.0,
        "assessed_value_change": -413,
        "assessed_value_change_pct": -1.0,
        "total_exemption_amount": 0,
        "net_assessed_value": 40798,
        "assessment_date": "2024-01-15"
      },
      {
        "tax_year": 2023,
        "assessed_value": 41211,
        "market_value": 41211,
        "land_value": 24417,
        "improvement_value": 16794,
        "land_value_percentage": 59.3,
        "improvement_value_percentage": 40.7,
        "market_to_assessed_ratio": 1.0,
        "assessed_value_change": 1962,
        "assessed_value_change_pct": 5.0,
        "total_exemption_amount": 0,
        "net_assessed_value": 41211,
        "assessment_date": "2023-01-15"
      },
      {
        "tax_year": 2022,
        "assessed_value": 39249,
        "market_value": 39249,
        "land_value": 23255,
        "improvement_value": 15994,
        "land_value_percentage": 59.3,
        "improvement_value_percentage": 40.7,
        "market_to_assessed_ratio": 1.0,
        "assessed_value_change": 1509,
        "assessed_value_change_pct": 4.0,
        "total_exemption_amount": 0,
        "net_assessed_value": 39249,
        "assessment_date": "2022-01-15"
      },
      {
        "tax_year": 2021,
        "assessed_value": 37740,
        "market_value": 37740,
        "land_value": 22361,
        "improvement_value": 15379,
        "land_value_percentage": 59.3,
        "improvement_value_percentage": 40.7,
        "market_to_assessed_ratio": 1.0,
        "assessed_value_change": 0,
        "assessed_value_change_pct": 0,
        "total_exemption_amount": 0,
        "net_assessed_value": 37740,
        "assessment_date": "2021-01-15"
      }
    ]
  },
  "exemptions": {
    "parcel_id": "0023H00275000000",
    "exemptions": []
  },
  "appeals": {
    "parcel_id": "0023H00275000000",
    "summary": {},
    "appeals": []
  },
  "comparables": {
    "parcel_id": "0023H00275000000",
    "comparables": [
      {
        "parcel_id": "0023E00180000000",
        "address": "516 ARMANDALE ST",
        "city": "Ward 25",
        "zip_code": "15212",
        "current_owner_name": "516   ARMANDALE ST",
        "land_use_description": "SINGLE FAMILY",
        "acreage": null,
        "assessed_value": 42500,
        "market_value": 60500,
        "assessed_value_change_pct": -4.9,
        "distance_miles": 0.1
      },
      {
        "parcel_id": "0023F00156000000",
        "address": "1531 ARCH ST",
        "city": "Ward 25",
        "zip_code": "15212",
        "current_owner_name": "PO BOX 6447",
        "land_use_description": "SINGLE FAMILY",
        "acreage": null,
        "assessed_value": 42900,
        "market_value": 60900,
        "assessed_value_change_pct": -4.1,
        "distance_miles": 0.3
      },
      {
        "parcel_id": "0023D00246000000",
        "address": "1631 COMPROMISE ST",
        "city": "Ward 25",
        "zip_code": "15212",
        "current_owner_name": "1631   COMPROMISE ST",
        "land_use_description": "SINGLE FAMILY",
        "acreage": null,
        "assessed_value": 43000,
        "market_value": 43000,
        "assessed_value_change_pct": -4.5,
        "distance_miles": 0.5
      },
      {
        "parcel_id": "0023F00416000000",
        "address": "219 JACKSONIA ST",
        "city": "Ward 25",
        "zip_code": "15212",
        "current_owner_name": "219   JACKSONIA ST",
        "land_use_description": "SINGLE FAMILY",
        "acreage": null,
        "assessed_value": 43000,
        "market_value": 61000,
        "assessed_value_change_pct": -4.3,
        "distance_miles": 0.7
      },
      {
        "parcel_id": "0023K00042000000",
        "address": "408 SAMPSONIA WAY",
        "city": "Ward 25",
        "zip_code": "15212",
        "current_owner_name": "324   SAMPSONIA WAY",
        "land_use_description": "ROWHOUSE",
        "acreage": null,
        "assessed_value": 42400,
        "market_value": 42400,
        "assessed_value_change_pct": -4.3,
        "distance_miles": 0.9
      },
      {
        "parcel_id": "0046S00153000000",
        "address": "630 TOBOGGAN ST",
        "city": "Ward 25",
        "zip_code": "15212",
        "current_owner_name": "414   GRANT ST  RM 200",
        "land_use_description": "SINGLE FAMILY",
        "acreage": null,
        "assessed_value": 42400,
        "market_value": 42400,
        "assessed_value_change_pct": -1.1,
        "distance_miles": 1.1
      }
    ]
  }
}