{
  "parcel": {
    "parcel_id": "0049G00037000000",
    "address": "358 42ND ST",
    "city": "10902",
    "zip_code": "15201",
    "county": "Allegheny",
    "current_owner_name": "358   42ND ST",
    "current_mailing_address": "358   42ND ST",
    "current_ownership_type": "REGULAR-ETAL",
    "land_use_code": null,
    "land_use_description": "SINGLE FAMILY",
    "acreage": 0.043,
    "latitude": 40.46488,
    "longitude": -79.94224
  },
  "assessments": {
    "parcel_id": "0049G00037000000",
    "assessments": [
      {
        "tax_year": 2026,
        "assessed_value": 72600,
        "market_value": 72600,
        "land_value": 17500,
        "improvement_value": 55100,
        "land_value_percentage": 24.1,
        "improvement_value_percentage": 75.9,
        "market_to_assessed_ratio": 1.0,
        "assessed_value_change": 4513,
        "assessed_value_change_pct": 6.63,
        "total_exemption_amount": 0,
        "net_assessed_value": 72600,
        "assessment_date": "2026-01-15"
      },
      {
        "tax_year": 2025,
        "assessed_value": 68087,
        "market_value": 68087,
        "land_value": 16412,
        "improvement_value": 51675,
        "land_value_percentage": 24.1,
        "improvement_value_percentage": 75.9,
        "market_to_assessed_ratio": 1.0,
        "assessed_value_change": 1983,
        "assessed_value_change_pct": 3.0,
        "total_exemption_amount": 0,
        "net_assessed_value": 68087,
        "assessment_date": "2025-01-15"
      },
      {
        "tax_year": 2024,
        "assessed_value": 66104,
        "market_value": 66104,
        "land_value": 15934,
        "improvement_value": 50170,
        "land_value_percentage": 24.1,
        "improvement_value_percentage": 75.9,
        "market_to_assessed_ratio": 1.0,
        "assessed_value_change": 1296,
        "assessed_value_change_pct": 2.0,
        "total_exemption_amount": 0,
        "net_assessed_value": 66104,
        "assessment_date": "2024-01-15"
      },
      {
        "tax_year": 2023,
        "assessed_value": 64808,
        "market_value": 64808,
        "land_value": 15621,
        "improvement_value": 49187,
        "land_value_percentage": 24.1,
        "improvement_value_percentage": 75.9,
        "market_to_assessed_ratio": 1.0,
        "assessed_value_change": 641,
        "assessed_value_change_pct": 1.0,
        "total_exemption_amount": 0,
        "net_assessed_value": 64808,
        "assessment_date": "2023-01-15"
      },
      {
        "tax_year": 2022,
        "assessed_value": 64167,
        "market_value": 64167,
        "land_value": 15467,
        "improvement_value": 48700,
        "land_value_percentage": 24.1,
        "improvement_value_percentage": 75.9,
        "market_to_assessed_ratio": 1.0,
        "assessed_value_change": 0,
        "assessed_value_change_pct": 0.0,
        "total_exemption_amount": 0,
        "net_assessed_value": 64167,
        "assessment_date": "2022-01-15"
      },
      {
        "tax_year": 2021,
        "assessed_value": 64167,
        "market_value": 64167,
        "land_value": 15467,
        "improvement_value": 48700,
        "land_value_percentage": 24.1,
        "improvement_value_percentage": 75.9,
        "market_to_assessed_ratio": 1.0,
        "assessed_value_change": 0,
        "assessed_value_change_pct": 0,
        "total_exemption_amount": 0,
        "net_assessed_value": 64167,
        "assessment_date": "2021-01-15"
      }
    ]
  },
  "exemptions": {
    "parcel_id": "0049G00037000000",
    "exemptions": []
  },
  "appeals": {
    "parcel_id": "0049G00037000000",
    "summary": {},
    "appeals": []
  },
  "comparables": {
    "parcel_id": "0049G00037000000",
    "comparables": [
      {
        "parcel_id": "0049C00147000000",
        "address": "254 46TH ST",
        "city": "10902",
        "zip_code": "15201",
        "current_owner_name": "5101   KEYSTONE ST  # 3",
        "land_use_description": "ROWHOUSE",
        "acreage": null,
        "assessed_value": 72700,
        "market_value": 72700,
        "assessed_value_change_pct": -3.1,
        "distance_miles": 0.1
      },
      {
        "parcel_id": "0049C00149000000",
        "address": "250 46TH ST",
        "city": "10902",
        "zip_code": "15201",
        "current_owner_name": "763   ALLEGHENY AVE",
        "land_use_description": "ROWHOUSE",
        "acreage": null,
        "assessed_value": 72300,
        "market_value": 72300,
        "assessed_value_change_pct": -2.7,
        "distance_miles": 0.3
      },
      {
        "parcel_id": "0049G00260000000",
        "address": "4419 GARWOOD WAY",
        "city": "10902",
        "zip_code": "15201",
        "current_owner_name": "4419   GARWOOD WAY",
        "land_use_description": "SINGLE FAMILY",
        "acreage": null,
        "assessed_value": 72300,
        "market_value": 72300,
        "assessed_value_change_pct": -3.1,
        "distance_miles": 0.5
      },
      {
        "parcel_id": "0049A00121000000",
        "address": "4110 FOSTER ST",
        "city": "10902",
        "zip_code": "15201",
        "current_owner_name": "2753   SHAMROCK DR",
        "land_use_description": "SINGLE FAMILY",
        "acreage": null,
        "assessed_value": 73000,
        "market_value": 73000,
        "assessed_value_change_pct": -5.1,
        "distance_miles": 0.7
      },
      {
        "parcel_id": "0049C00156000200",
        "address": "240 46TH ST",
        "city": "10902",
        "zip_code": "15201",
        "current_owner_name": "240 1/2  46TH ST",
        "land_use_description": "ROWHOUSE",
        "acreage": null,
        "assessed_value": 73000,
        "market_value": 73000,
        "assessed_value_change_pct": -2.7,
        "distance_miles": 0.9
      },
      {
        "parcel_id": "0049G00183000000",
        "address": "4213 GENEVA ST",
        "city": "10902",
        "zip_code": "15201",
        "current_owner_name": "338   44TH ST",
        "land_use_description": "SINGLE FAMILY",
        "acreage": null,
        "assessed_value": 73000,
        "market_value": 73000,
        "assessed_value_change_pct": -2.3,
        "distance_miles": 1.1
      }
    ]
  }
}