{
  "parcel": {
    "parcel_id": "0049G00017000000",
    "address": "315 MAIN ST",
    "city": "10902",
    "zip_code": "15201",
    "county": "Allegheny",
    "current_owner_name": "315   MAIN ST",
    "current_mailing_address": "315   MAIN ST",
    "current_ownership_type": "REGULAR",
    "land_use_code": null,
    "land_use_description": "ROWHOUSE",
    "acreage": 0.046,
    "latitude": 40.46464,
    "longitude": -79.9444
  },
  "assessments": {
    "parcel_id": "0049G00017000000",
    "assessments": [
      {
        "tax_year": 2026,
        "assessed_value": 293400,
        "market_value": 311400,
        "land_value": 18000,
        "improvement_value": 275400,
        "land_value_percentage": 6.1,
        "improvement_value_percentage": 93.9,
        "market_to_assessed_ratio": 1.06,
        "assessed_value_change": 21140,
        "assessed_value_change_pct": 7.76,
        "total_exemption_amount": 18000,
        "net_assessed_value": 275400,
        "assessment_date": "2026-01-15"
      },
      {
        "tax_year": 2025,
        "assessed_value": 272260,
        "market_value": 288963,
        "land_value": 16703,
        "improvement_value": 255557,
        "land_value_percentage": 6.1,
        "improvement_value_percentage": 93.9,
        "market_to_assessed_ratio": 1.06,
        "assessed_value_change": 2695,
        "assessed_value_change_pct": 1.0,
        "total_exemption_amount": 18000,
        "net_assessed_value": 254260,
        "assessment_date": "2025-01-15"
      },
      {
        "tax_year": 2024,
        "assessed_value": 269565,
        "market_value": 286102,
        "land_value": 16537,
        "improvement_value": 253028,
        "land_value_percentage": 6.1,
        "improvement_value_percentage": 93.9,
        "market_to_assessed_ratio": 1.06,
        "assessed_value_change": 0,
        "assessed_value_change_pct": 0.0,
        "total_exemption_amount": 18000,
        "net_assessed_value": 251565,
        "assessment_date": "2024-01-15"
      },
      {
        "tax_year": 2023,
        "assessed_value": 269565,
        "market_value": 286102,
        "land_value": 16537,
        "improvement_value": 253028,
        "land_value_percentage": 6.1,
        "improvement_value_percentage": 93.9,
        "market_to_assessed_ratio": 1.06,
        "assessed_value_change": -2723,
        "assessed_value_change_pct": -1.0,
        "total_exemption_amount": 18000,
        "net_assessed_value": 251565,
        "assessment_date": "2023-01-15"
      },
      {
        "tax_year": 2022,
        "assessed_value": 272288,
        "market_value": 288992,
        "land_value": 16704,
        "improvement_value": 255584,
        "land_value_percentage": 6.1,
        "improvement_value_percentage": 93.9,
        "market_to_assessed_ratio": 1.06,
        "assessed_value_change": 12966,
        "assessed_value_change_pct": 5.0,
        "total_exemption_amount": 18000,
        "net_assessed_value": 254288,
        "assessment_date": "2022-01-15"
      },
      {
        "tax_year": 2021,
        "assessed_value": 259322,
        "market_value": 275231,
        "land_value": 15909,
        "improvement_value": 243413,
        "land_value_percentage": 6.1,
        "improvement_value_percentage": 93.9,
        "market_to_assessed_ratio": 1.06,
        "assessed_value_change": 0,
        "assessed_value_change_pct": 0,
        "total_exemption_amount": 18000,
        "net_assessed_value": 241322,
        "assessment_date": "2021-01-15"
      }
    ]
  },
  "exemptions": {
    "parcel_id": "0049G00017000000",
    "exemptions": [
      {
        "tax_year": 2026,
        "total_exemption_amount": 18000,
        "total_exemption_count": 1,
        "homestead_exemption_amount": 18000,
        "senior_exemption_amount": 0,
        "veteran_exemption_amount": 0,
        "disability_exemption_amount": 0,
        "homestead_count": 1,
        "senior_count": 0,
        "veteran_count": 0,
        "disability_count": 0,
        "active_exemptions": 1,
        "pending_exemptions": 0,
        "expired_exemptions": 0,
        "exemption_types": "HOMESTEAD"
      },
      {
        "tax_year": 2025,
        "total_exemption_amount": 18000,
        "total_exemption_count": 1,
        "homestead_exemption_amount": 18000,
        "senior_exemption_amount": 0,
        "veteran_exemption_amount": 0,
        "disability_exemption_amount": 0,
        "homestead_count": 1,
        "senior_count": 0,
        "veteran_count": 0,
        "disability_count": 0,
        "active_exemptions": 1,
        "pending_exemptions": 0,
        "expired_exemptions": 0,
        "exemption_types": "HOMESTEAD"
      },
      {
        "tax_year": 2024,
        "total_exemption_amount": 18000,
        "total_exemption_count": 1,
        "homestead_exemption_amount": 18000,
        "senior_exemption_amount": 0,
        "veteran_exemption_amount": 0,
        "disability_exemption_amount": 0,
        "homestead_count": 1,
        "senior_count": 0,
        "veteran_count": 0,
        "disability_count": 0,
        "active_exemptions": 1,
        "pending_exemptions": 0,
        "expired_exemptions": 0,
        "exemption_types": "HOMESTEAD"
      }
    ]
  },
  "appeals": {
    "parcel_id": "0049G00017000000",
    "summary": {
      "total_appeals": 1,
      "approved_count": 0,
      "denied_count": 1,
      "success_rate_pct": 0.0,
      "avg_value_reduction": 0,
      "total_value_reduction": 0,
      "first_appeal_date": "9-Jun-17",
      "most_recent_appeal_date": "9-Jun-17",
      "latest_appeal_status": "approved"
    },
    "appeals": [
      {
        "appeal_id": "WPRDC-15740-2017",
        "filed_date": "9-Jun-17",
        "hearing_date": "9-Jun-17",
        "appeal_status": "approved",
        "original_value": 115800,
        "requested_value": 115800,
        "final_value": 311400,
        "value_reduction": 0,
        "reduction_percentage": -168.91,
        "resolution_notes": "ANNUAL"
      }
    ]
  },
  "comparables": {
    "parcel_id": "0049G00017000000",
    "comparables": [
      {
        "parcel_id": "0080P00156000000",
        "address": "4522 PLUMMER ST",
        "city": "10902",
        "zip_code": "15201",
        "current_owner_name": "4522   PLUMMER ST",
        "land_use_description": "ROWHOUSE",
        "acreage": null,
        "assessed_value": 293400,
        "market_value": 311400,
        "assessed_value_change_pct": -1.5,
        "distance_miles": 0.1
      },
      {
        "parcel_id": "0080P00102000D00",
        "address": "173 45TH ST",
        "city": "10902",
        "zip_code": "15201",
        "current_owner_name": "173   45TH ST  # D",
        "land_use_description": "ROWHOUSE",
        "acreage": null,
        "assessed_value": 293200,
        "market_value": 311200,
        "assessed_value_change_pct": 0.7,
        "distance_miles": 0.3
      },
      {
        "parcel_id": "0049A00027000000",
        "address": "113 42ND ST",
        "city": "10902",
        "zip_code": "15201",
        "current_owner_name": "1547   ELDORADO DR",
        "land_use_description": "ROWHOUSE",
        "acreage": null,
        "assessed_value": 290500,
        "market_value": 290500,
        "assessed_value_change_pct": -4.1,
        "distance_miles": 0.5
      },
      {
        "parcel_id": "0049A00155000000",
        "address": "127 BANNER WAY",
        "city": "10902",
        "zip_code": "15201",
        "current_owner_name": "125   CHESTNUT LN",
        "land_use_description": "SINGLE FAMILY",
        "acreage": null,
        "assessed_value": 290300,
        "market_value": 290300,
        "assessed_value_change_pct": -3.7,
        "distance_miles": 0.7
      },
      {
        "parcel_id": "0049F00274000000",
        "address": "326 42ND ST",
        "city": "10902",
        "zip_code": "15201",
        "current_owner_name": "326   42ND ST",
        "land_use_description": "SINGLE FAMILY",
        "acreage": null,
        "assessed_value": 296600,
        "market_value": 314600,
        "assessed_value_change_pct": -2.3,
        "distance_miles": 0.9
      },
      {
        "parcel_id": "0049B00146000000",
        "address": "190 42ND ST",
        "city": "10902",
        "zip_code": "15201",
        "current_owner_name": "190   42ND ST",
        "land_use_description": "TOWNHOUSE",
        "acreage": null,
        "assessed_value": 290100,
        "market_value": 308100,
        "assessed_value_change_pct": -3.5,
        "distance_miles": 1.1
      }
    ]
  }
}