{
  "parcel": {
    "parcel_id": "0049J00272000000",
    "address": "259 38TH ST",
    "city": "10601",
    "zip_code": "15201",
    "county": "Allegheny",
    "current_owner_name": "157   TOPSFIELD RD",
    "current_mailing_address": "157   TOPSFIELD RD",
    "current_ownership_type": "REGULAR-ETUX OR ET VIR",
    "land_use_code": null,
    "land_use_description": "ROWHOUSE",
    "acreage": 0.036,
    "latitude": 40.46536,
    "longitude": -79.9642
  },
  "assessments": {
    "parcel_id": "0049J00272000000",
    "assessments": [
      {
        "tax_year": 2026,
        "assessed_value": 125000,
        "market_value": 125000,
        "land_value": 12300,
        "improvement_value": 112700,
        "land_value_percentage": 9.8,
        "improvement_value_percentage": 90.2,
        "market_to_assessed_ratio": 1.0,
        "assessed_value_change": 5562,
        "assessed_value_change_pct": 4.66,
        "total_exemption_amount": 0,
        "net_assessed_value": 125000,
        "assessment_date": "2026-01-15"
      },
      {
        "tax_year": 2025,
        "assessed_value": 119438,
        "market_value": 119438,
        "land_value": 11752,
        "improvement_value": 107686,
        "land_value_percentage": 9.8,
        "improvement_value_percentage": 90.2,
        "market_to_assessed_ratio": 1.0,
        "assessed_value_change": 0,
        "assessed_value_change_pct": 0.0,
        "total_exemption_amount": 0,
        "net_assessed_value": 119438,
        "assessment_date": "2025-01-15"
      },
      {
        "tax_year": 2024,
        "assessed_value": 119438,
        "market_value": 119438,
        "land_value": 11752,
        "improvement_value": 107686,
        "land_value_percentage": 9.8,
        "improvement_value_percentage": 90.2,
        "market_to_assessed_ratio": 1.0,
        "assessed_value_change": -1207,
        "assessed_value_change_pct": -1.0,
        "total_exemption_amount": 0,
        "net_assessed_value": 119438,
        "assessment_date": "2024-01-15"
      },
      {
        "tax_year": 2023,
        "assessed_value": 120645,
        "market_value": 120645,
        "land_value": 11871,
        "improvement_value": 108774,
        "land_value_percentage": 9.8,
        "improvement_value_percentage": 90.2,
        "market_to_assessed_ratio": 1.0,
        "assessed_value_change": 5745,
        "assessed_value_change_pct": 5.0,
        "total_exemption_amount": 0,
        "net_assessed_value": 120645,
        "assessment_date": "2023-01-15"
      },
      {
        "tax_year": 2022,
        "assessed_value": 114900,
        "market_value": 114900,
        "land_value": 11306,
        "improvement_value": 103594,
        "land_value_percentage": 9.8,
        "improvement_value_percentage": 90.2,
        "market_to_assessed_ratio": 1.0,
        "assessed_value_change": 4419,
        "assessed_value_change_pct": 4.0,
        "total_exemption_amount": 0,
        "net_assessed_value": 114900,
        "assessment_date": "2022-01-15"
      },
      {
        "tax_year": 2021,
        "assessed_value": 110481,
        "market_value": 110481,
        "land_value": 10871,
        "improvement_value": 99610,
        "land_value_percentage": 9.8,
        "improvement_value_percentage": 90.2,
        "market_to_assessed_ratio": 1.0,
        "assessed_value_change": 0,
        "assessed_value_change_pct": 0,
        "total_exemption_amount": 0,
        "net_assessed_value": 110481,
        "assessment_date": "2021-01-15"
      }
    ]
  },
  "exemptions": {
    "parcel_id": "0049J00272000000",
    "exemptions": []
  },
  "appeals": {
    "parcel_id": "0049J00272000000",
    "summary": {},
    "appeals": []
  },
  "comparables": {
    "parcel_id": "0049J00272000000",
    "comparables": [
      {
        "parcel_id": "0049E00095000000",
        "address": "182 39TH ST",
        "city": "10601",
        "zip_code": "15201",
        "current_owner_name": "PO BOX 36",
        "land_use_description": "ROWHOUSE",
        "acreage": null,
        "assessed_value": 125000,
        "market_value": 125000,
        "assessed_value_change_pct": -2.3,
        "distance_miles": 0.1
      },
      {
        "parcel_id": "0026B00015000A00",
        "address": "3724 LIBERTY AVE",
        "city": "10601",
        "zip_code": "15201",
        "current_owner_name": "207   ELMTREE RD",
        "land_use_description": "ROWHOUSE",
        "acreage": null,
        "assessed_value": 124500,
        "market_value": 124500,
        "assessed_value_change_pct": -2.1,
        "distance_miles": 0.3
      },
      {
        "parcel_id": "0049K00005000000",
        "address": "285 38TH ST",
        "city": "10601",
        "zip_code": "15201",
        "current_owner_name": "285   38TH ST",
        "land_use_description": "TWO FAMILY",
        "acreage": null,
        "assessed_value": 125700,
        "market_value": 143700,
        "assessed_value_change_pct": -2.9,
        "distance_miles": 0.5
      },
      {
        "parcel_id": "0049N00128000A00",
        "address": "3440 PENN AVE",
        "city": "10601",
        "zip_code": "15201",
        "current_owner_name": "3440   PENN AVE",
        "land_use_description": "TOWNHOUSE",
        "acreage": null,
        "assessed_value": 125700,
        "market_value": 143700,
        "assessed_value_change_pct": 2.3,
        "distance_miles": 0.7
      },
      {
        "parcel_id": "0049P00054000000",
        "address": "3714 PENN AVE",
        "city": "10601",
        "zip_code": "15201",
        "current_owner_name": "5881   ELLSWORTH AVE",
        "land_use_description": "TWO FAMILY",
        "acreage": null,
        "assessed_value": 124300,
        "market_value": 124300,
        "assessed_value_change_pct": -1.1,
        "distance_miles": 0.9
      },
      {
        "parcel_id": "0026K00043000000",
        "address": "3453 RIDGWAY ST",
        "city": "10601",
        "zip_code": "15213",
        "current_owner_name": "3453   RIDGWAY ST",
        "land_use_description": "SINGLE FAMILY",
        "acreage": null,
        "assessed_value": 124300,
        "market_value": 142300,
        "assessed_value_change_pct": -3.5,
        "distance_miles": 1.1
      }
    ]
  }
}