{
  "parcel": {
    "parcel_id": "0083B00115000000",
    "address": "5527 HAYS ST",
    "city": "11103",
    "zip_code": "15206",
    "county": "Allegheny",
    "current_owner_name": "412   MAPLE AVE",
    "current_mailing_address": "412   MAPLE AVE",
    "current_ownership_type": "REGULAR",
    "land_use_code": null,
    "land_use_description": "THREE FAMILY",
    "acreage": 0.122,
    "latitude": 40.46078,
    "longitude": -79.91068
  },
  "assessments": {
    "parcel_id": "0083B00115000000",
    "assessments": [
      {
        "tax_year": 2026,
        "assessed_value": 98700,
        "market_value": 98700,
        "land_value": 45000,
        "improvement_value": 53700,
        "land_value_percentage": 45.6,
        "improvement_value_percentage": 54.4,
        "market_to_assessed_ratio": 1.0,
        "assessed_value_change": 4392,
        "assessed_value_change_pct": 4.66,
        "total_exemption_amount": 0,
        "net_assessed_value": 98700,
        "assessment_date": "2026-01-15"
      },
      {
        "tax_year": 2025,
        "assessed_value": 94308,
        "market_value": 94308,
        "land_value": 42997,
        "improvement_value": 51311,
        "land_value_percentage": 45.6,
        "improvement_value_percentage": 54.4,
        "market_to_assessed_ratio": 1.0,
        "assessed_value_change": 0,
        "assessed_value_change_pct": 0.0,
        "total_exemption_amount": 0,
        "net_assessed_value": 94308,
        "assessment_date": "2025-01-15"
      },
      {
        "tax_year": 2024,
        "assessed_value": 94308,
        "market_value": 94308,
        "land_value": 42997,
        "improvement_value": 51311,
        "land_value_percentage": 45.6,
        "improvement_value_percentage": 54.4,
        "market_to_assessed_ratio": 1.0,
        "assessed_value_change": -953,
        "assessed_value_change_pct": -1.0,
        "total_exemption_amount": 0,
        "net_assessed_value": 94308,
        "assessment_date": "2024-01-15"
      },
      {
        "tax_year": 2023,
        "assessed_value": 95261,
        "market_value": 95261,
        "land_value": 43432,
        "improvement_value": 51829,
        "land_value_percentage": 45.6,
        "improvement_value_percentage": 54.4,
        "market_to_assessed_ratio": 1.0,
        "assessed_value_change": 4536,
        "assessed_value_change_pct": 5.0,
        "total_exemption_amount": 0,
        "net_assessed_value": 95261,
        "assessment_date": "2023-01-15"
      },
      {
        "tax_year": 2022,
        "assessed_value": 90725,
        "market_value": 90725,
        "land_value": 41363,
        "improvement_value": 49362,
        "land_value_percentage": 45.6,
        "improvement_value_percentage": 54.4,
        "market_to_assessed_ratio": 1.0,
        "assessed_value_change": 3489,
        "assessed_value_change_pct": 4.0,
        "total_exemption_amount": 0,
        "net_assessed_value": 90725,
        "assessment_date": "2022-01-15"
      },
      {
        "tax_year": 2021,
        "assessed_value": 87236,
        "market_value": 87236,
        "land_value": 39773,
        "improvement_value": 47463,
        "land_value_percentage": 45.6,
        "improvement_value_percentage": 54.4,
        "market_to_assessed_ratio": 1.0,
        "assessed_value_change": 0,
        "assessed_value_change_pct": 0,
        "total_exemption_amount": 0,
        "net_assessed_value": 87236,
        "assessment_date": "2021-01-15"
      }
    ]
  },
  "exemptions": {
    "parcel_id": "0083B00115000000",
    "exemptions": []
  },
  "appeals": {
    "parcel_id": "0083B00115000000",
    "summary": {},
    "appeals": []
  },
  "comparables": {
    "parcel_id": "0083B00115000000",
    "comparables": [
      {
        "parcel_id": "0082P00246000000",
        "address": "940 N NEGLEY AVE",
        "city": "11103",
        "zip_code": "15206",
        "current_owner_name": "940  N NEGLEY AVE",
        "land_use_description": "TWO FAMILY",
        "acreage": null,
        "assessed_value": 98800,
        "market_value": 116800,
        "assessed_value_change_pct": -1.1,
        "distance_miles": 0.1
      },
      {
        "parcel_id": "0083B00076000000",
        "address": "5519 BAYWOOD ST",
        "city": "11103",
        "zip_code": "15206",
        "current_owner_name": "946   HIGHVIEW RD",
        "land_use_description": "THREE FAMILY",
        "acreage": null,
        "assessed_value": 98900,
        "market_value": 98900,
        "assessed_value_change_pct": -3.5,
        "distance_miles": 0.3
      },
      {
        "parcel_id": "0050H00369000000",
        "address": "406 N AIKEN AVE",
        "city": "11103",
        "zip_code": "15206",
        "current_owner_name": "171   INDUSTRY DR  STE 150",
        "land_use_description": "ROWHOUSE",
        "acreage": null,
        "assessed_value": 99000,
        "market_value": 99000,
        "assessed_value_change_pct": -2.5,
        "distance_miles": 0.5
      },
      {
        "parcel_id": "0050H00371000000",
        "address": "404 N AIKEN AVE",
        "city": "11103",
        "zip_code": "15206",
        "current_owner_name": "1171   INDUSTRY DR  STE 150",
        "land_use_description": "ROWHOUSE",
        "acreage": null,
        "assessed_value": 99000,
        "market_value": 99000,
        "assessed_value_change_pct": -3.9,
        "distance_miles": 0.7
      },
      {
        "parcel_id": "0050H00373000000",
        "address": "402 N AIKEN AVE",
        "city": "11103",
        "zip_code": "15206",
        "current_owner_name": "171   INDUSTRY DR  STE 150",
        "land_use_description": "ROWHOUSE",
        "acreage": null,
        "assessed_value": 99000,
        "market_value": 99000,
        "assessed_value_change_pct": -3.5,
        "distance_miles": 0.9
      },
      {
        "parcel_id": "0083B00219000000",
        "address": "708 N NEGLEY AVE",
        "city": "11103",
        "zip_code": "15206",
        "current_owner_name": "708  N NEGLEY AVE",
        "land_use_description": "SINGLE FAMILY",
        "acreage": null,
        "assessed_value": 99000,
        "market_value": 117000,
        "assessed_value_change_pct": -3.7,
        "distance_miles": 1.1
      }
    ]
  }
}