{
  "parcel": {
    "parcel_id": "0087P00082000000",
    "address": "4005 MURRAY AVE",
    "city": "15th Ward (Pittsburgh)",
    "zip_code": "15217",
    "county": "Allegheny",
    "current_owner_name": "26   TIMBERLINE CT",
    "current_mailing_address": "26   TIMBERLINE CT",
    "current_ownership_type": "CORPORATION",
    "land_use_code": null,
    "land_use_description": "CHURCHES, PUBLIC WORSHIP",
    "acreage": 0.2,
    "latitude": 40.4218,
    "longitude": -79.92866
  },
  "assessments": {
    "parcel_id": "0087P00082000000",
    "assessments": [
      {
        "tax_year": 2026,
        "assessed_value": 424700,
        "market_value": 424700,
        "land_value": 87300,
        "improvement_value": 337400,
        "land_value_percentage": 20.6,
        "improvement_value_percentage": 79.4,
        "market_to_assessed_ratio": 1.0,
        "assessed_value_change": 18895,
        "assessed_value_change_pct": 4.66,
        "total_exemption_amount": 0,
        "net_assessed_value": 424700,
        "assessment_date": "2026-01-15"
      },
      {
        "tax_year": 2025,
        "assessed_value": 405805,
        "market_value": 405805,
        "land_value": 83416,
        "improvement_value": 322389,
        "land_value_percentage": 20.6,
        "improvement_value_percentage": 79.4,
        "market_to_assessed_ratio": 1.0,
        "assessed_value_change": 0,
        "assessed_value_change_pct": 0.0,
        "total_exemption_amount": 0,
        "net_assessed_value": 405805,
        "assessment_date": "2025-01-15"
      },
      {
        "tax_year": 2024,
        "assessed_value": 405805,
        "market_value": 405805,
        "land_value": 83416,
        "improvement_value": 322389,
        "land_value_percentage": 20.6,
        "improvement_value_percentage": 79.4,
        "market_to_assessed_ratio": 1.0,
        "assessed_value_change": -4100,
        "assessed_value_change_pct": -1.0,
        "total_exemption_amount": 0,
        "net_assessed_value": 405805,
        "assessment_date": "2024-01-15"
      },
      {
        "tax_year": 2023,
        "assessed_value": 409905,
        "market_value": 409905,
        "land_value": 84258,
        "improvement_value": 325647,
        "land_value_percentage": 20.6,
        "improvement_value_percentage": 79.4,
        "market_to_assessed_ratio": 1.0,
        "assessed_value_change": 19519,
        "assessed_value_change_pct": 5.0,
        "total_exemption_amount": 0,
        "net_assessed_value": 409905,
        "assessment_date": "2023-01-15"
      },
      {
        "tax_year": 2022,
        "assessed_value": 390386,
        "market_value": 390386,
        "land_value": 80246,
        "improvement_value": 310140,
        "land_value_percentage": 20.6,
        "improvement_value_percentage": 79.4,
        "market_to_assessed_ratio": 1.0,
        "assessed_value_change": 15014,
        "assessed_value_change_pct": 4.0,
        "total_exemption_amount": 0,
        "net_assessed_value": 390386,
        "assessment_date": "2022-01-15"
      },
      {
        "tax_year": 2021,
        "assessed_value": 375372,
        "market_value": 375372,
        "land_value": 77160,
        "improvement_value": 298212,
        "land_value_percentage": 20.6,
        "improvement_value_percentage": 79.4,
        "market_to_assessed_ratio": 1.0,
        "assessed_value_change": 0,
        "assessed_value_change_pct": 0,
        "total_exemption_amount": 0,
        "net_assessed_value": 375372,
        "assessment_date": "2021-01-15"
      }
    ]
  },
  "exemptions": {
    "parcel_id": "0087P00082000000",
    "exemptions": []
  },
  "appeals": {
    "parcel_id": "0087P00082000000",
    "summary": {},
    "appeals": []
  },
  "comparables": {
    "parcel_id": "0087P00082000000",
    "comparables": [
      {
        "parcel_id": "0088B00056000002",
        "address": "3503 BEECHWOOD BLVD",
        "city": "15th Ward (Pittsburgh)",
        "zip_code": "15217",
        "current_owner_name": "3503   BEECHWOOD BLVD",
        "land_use_description": "CHURCHES, PUBLIC WORSHIP",
        "acreage": null,
        "assessed_value": 421050,
        "market_value": 421050,
        "assessed_value_change_pct": -2.5,
        "distance_miles": 0.1
      },
      {
        "parcel_id": "0088E00333000000",
        "address": "805 HAZELWOOD AVE",
        "city": "15th Ward (Pittsburgh)",
        "zip_code": "15217",
        "current_owner_name": "128   PARKSIDE DR",
        "land_use_description": "APART: 5-19 UNITS",
        "acreage": null,
        "assessed_value": 436000,
        "market_value": 436000,
        "assessed_value_change_pct": -2.7,
        "distance_miles": 0.3
      },
      {
        "parcel_id": "0088F00038000000",
        "address": "4371 MURRAY AVE",
        "city": "15th Ward (Pittsburgh)",
        "zip_code": "15217",
        "current_owner_name": "111   CLIFTON AVE",
        "land_use_description": "OFFICE/APARTMENTS OVER",
        "acreage": null,
        "assessed_value": 407300,
        "market_value": 407300,
        "assessed_value_change_pct": -2.1,
        "distance_miles": 0.5
      },
      {
        "parcel_id": "0088F00001000000",
        "address": "4370 MURRAY AVE",
        "city": "15th Ward (Pittsburgh)",
        "zip_code": "15217",
        "current_owner_name": "1000   GRANDVIEW AVE  APT 103",
        "land_use_description": "RETL/APT'S OVER",
        "acreage": null,
        "assessed_value": 368200,
        "market_value": 368200,
        "assessed_value_change_pct": -4.1,
        "distance_miles": 0.7
      },
      {
        "parcel_id": "0088E00170000000",
        "address": "749 HAZELWOOD AVE",
        "city": "15th Ward (Pittsburgh)",
        "zip_code": "15217",
        "current_owner_name": "PO BOX 81746",
        "land_use_description": "APART: 5-19 UNITS",
        "acreage": null,
        "assessed_value": 351200,
        "market_value": 351200,
        "assessed_value_change_pct": -2.9,
        "distance_miles": 0.9
      },
      {
        "parcel_id": "0088B00048000000",
        "address": "3515 BEECHWOOD BLVD",
        "city": "15th Ward (Pittsburgh)",
        "zip_code": "15217",
        "current_owner_name": "700   ARDMORE BLVD",
        "land_use_description": "APART: 5-19 UNITS",
        "acreage": null,
        "assessed_value": 350000,
        "market_value": 350000,
        "assessed_value_change_pct": -2.7,
        "distance_miles": 1.1
      }
    ]
  }
}