{
  "parcel": {
    "parcel_id": "0124H00045000700",
    "address": "6511 CLIFFORD ST",
    "city": "11202",
    "zip_code": "15206",
    "county": "Allegheny",
    "current_owner_name": "6375   PENN AVE  STE #1078",
    "current_mailing_address": "6375   PENN AVE  STE #1078",
    "current_ownership_type": "CORPORATION",
    "land_use_code": null,
    "land_use_description": "ROWHOUSE",
    "acreage": 0.024,
    "latitude": 40.4621,
    "longitude": -79.91848
  },
  "assessments": {
    "parcel_id": "0124H00045000700",
    "assessments": [
      {
        "tax_year": 2026,
        "assessed_value": 12200,
        "market_value": 12200,
        "land_value": 1400,
        "improvement_value": 10800,
        "land_value_percentage": 11.5,
        "improvement_value_percentage": 88.5,
        "market_to_assessed_ratio": 1.0,
        "assessed_value_change": 303,
        "assessed_value_change_pct": 2.55,
        "total_exemption_amount": 0,
        "net_assessed_value": 12200,
        "assessment_date": "2026-01-15"
      },
      {
        "tax_year": 2025,
        "assessed_value": 11897,
        "market_value": 11897,
        "land_value": 1365,
        "improvement_value": 10532,
        "land_value_percentage": 11.5,
        "improvement_value_percentage": 88.5,
        "market_to_assessed_ratio": 1.0,
        "assessed_value_change": 457,
        "assessed_value_change_pct": 3.99,
        "total_exemption_amount": 0,
        "net_assessed_value": 11897,
        "assessment_date": "2025-01-15"
      },
      {
        "tax_year": 2024,
        "assessed_value": 11440,
        "market_value": 11440,
        "land_value": 1312,
        "improvement_value": 10128,
        "land_value_percentage": 11.5,
        "improvement_value_percentage": 88.5,
        "market_to_assessed_ratio": 1.0,
        "assessed_value_change": 333,
        "assessed_value_change_pct": 3.0,
        "total_exemption_amount": 0,
        "net_assessed_value": 11440,
        "assessment_date": "2024-01-15"
      },
      {
        "tax_year": 2023,
        "assessed_value": 11107,
        "market_value": 11107,
        "land_value": 1274,
        "improvement_value": 9833,
        "land_value_percentage": 11.5,
        "improvement_value_percentage": 88.5,
        "market_to_assessed_ratio": 1.0,
        "assessed_value_change": 217,
        "assessed_value_change_pct": 1.99,
        "total_exemption_amount": 0,
        "net_assessed_value": 11107,
        "assessment_date": "2023-01-15"
      },
      {
        "tax_year": 2022,
        "assessed_value": 10890,
        "market_value": 10890,
        "land_value": 1249,
        "improvement_value": 9641,
        "land_value_percentage": 11.5,
        "improvement_value_percentage": 88.5,
        "market_to_assessed_ratio": 1.0,
        "assessed_value_change": 107,
        "assessed_value_change_pct": 0.99,
        "total_exemption_amount": 0,
        "net_assessed_value": 10890,
        "assessment_date": "2022-01-15"
      },
      {
        "tax_year": 2021,
        "assessed_value": 10783,
        "market_value": 10783,
        "land_value": 1237,
        "improvement_value": 9546,
        "land_value_percentage": 11.5,
        "improvement_value_percentage": 88.5,
        "market_to_assessed_ratio": 1.0,
        "assessed_value_change": 0,
        "assessed_value_change_pct": 0,
        "total_exemption_amount": 0,
        "net_assessed_value": 10783,
        "assessment_date": "2021-01-15"
      }
    ]
  },
  "exemptions": {
    "parcel_id": "0124H00045000700",
    "exemptions": []
  },
  "appeals": {
    "parcel_id": "0124H00045000700",
    "summary": {},
    "appeals": []
  },
  "comparables": {
    "parcel_id": "0124H00045000700",
    "comparables": [
      {
        "parcel_id": "0124G00049000000",
        "address": "6431 CLIFFORD ST",
        "city": "11202",
        "zip_code": "15206",
        "current_owner_name": "6431   CLIFFORD ST",
        "land_use_description": "SINGLE FAMILY",
        "acreage": null,
        "assessed_value": 12200,
        "market_value": 30200,
        "assessed_value_change_pct": -3.3,
        "distance_miles": 0.1
      },
      {
        "parcel_id": "0124H00045000900",
        "address": "6507 CLIFFORD ST",
        "city": "11202",
        "zip_code": "15206",
        "current_owner_name": "6375   PENN AVE  STE B",
        "land_use_description": "ROWHOUSE",
        "acreage": null,
        "assessed_value": 12200,
        "market_value": 12200,
        "assessed_value_change_pct": -2.1,
        "distance_miles": 0.3
      },
      {
        "parcel_id": "0124H00045001000",
        "address": "6505 CLIFFORD ST",
        "city": "11202",
        "zip_code": "15206",
        "current_owner_name": "6375   PENN AVE  STE B",
        "land_use_description": "ROWHOUSE",
        "acreage": null,
        "assessed_value": 12200,
        "market_value": 12200,
        "assessed_value_change_pct": -3.7,
        "distance_miles": 0.5
      },
      {
        "parcel_id": "0124H00045001100",
        "address": "6503 CLIFFORD ST",
        "city": "11202",
        "zip_code": "15206",
        "current_owner_name": "6375   PENN AVE  STE B",
        "land_use_description": "ROWHOUSE",
        "acreage": null,
        "assessed_value": 12200,
        "market_value": 12200,
        "assessed_value_change_pct": -3.5,
        "distance_miles": 0.7
      },
      {
        "parcel_id": "0124S00076000000",
        "address": "6641 ROWAN ST",
        "city": "11202",
        "zip_code": "15206",
        "current_owner_name": "PO BOX 4642",
        "land_use_description": "SINGLE FAMILY",
        "acreage": null,
        "assessed_value": 12200,
        "market_value": 12200,
        "assessed_value_change_pct": -0.9,
        "distance_miles": 0.9
      },
      {
        "parcel_id": "0172N00038000000",
        "address": "6926 CHURCHLAND ST",
        "city": "11202",
        "zip_code": "15206",
        "current_owner_name": "6926   CHURCHLAND ST",
        "land_use_description": "SINGLE FAMILY",
        "acreage": null,
        "assessed_value": 12200,
        "market_value": 30200,
        "assessed_value_change_pct": -1.7,
        "distance_miles": 1.1
      }
    ]
  }
}