{
  "parcel": {
    "parcel_id": "0933S00064000000",
    "address": "75 MAIN ST",
    "city": "Leet",
    "zip_code": "15003",
    "county": "Allegheny",
    "current_owner_name": "75   MAIN ST",
    "current_mailing_address": "75   MAIN ST",
    "current_ownership_type": "REGULAR-ETUX OR ET VIR",
    "land_use_code": null,
    "land_use_description": "SINGLE FAMILY",
    "acreage": 0.292,
    "latitude": 40.59186,
    "longitude": -80.21818
  },
  "assessments": {
    "parcel_id": "0933S00064000000",
    "assessments": [
      {
        "tax_year": 2026,
        "assessed_value": 202000,
        "market_value": 220000,
        "land_value": 14000,
        "improvement_value": 188000,
        "land_value_percentage": 6.9,
        "improvement_value_percentage": 93.1,
        "market_to_assessed_ratio": 1.09,
        "assessed_value_change": 12554,
        "assessed_value_change_pct": 6.63,
        "total_exemption_amount": 18000,
        "net_assessed_value": 184000,
        "assessment_date": "2026-01-15"
      },
      {
        "tax_year": 2025,
        "assessed_value": 189446,
        "market_value": 206327,
        "land_value": 13129,
        "improvement_value": 176317,
        "land_value_percentage": 6.9,
        "improvement_value_percentage": 93.1,
        "market_to_assessed_ratio": 1.09,
        "assessed_value_change": 5517,
        "assessed_value_change_pct": 3.0,
        "total_exemption_amount": 18000,
        "net_assessed_value": 171446,
        "assessment_date": "2025-01-15"
      },
      {
        "tax_year": 2024,
        "assessed_value": 183929,
        "market_value": 200318,
        "land_value": 12747,
        "improvement_value": 171182,
        "land_value_percentage": 6.9,
        "improvement_value_percentage": 93.1,
        "market_to_assessed_ratio": 1.09,
        "assessed_value_change": 3606,
        "assessed_value_change_pct": 2.0,
        "total_exemption_amount": 18000,
        "net_assessed_value": 165929,
        "assessment_date": "2024-01-15"
      },
      {
        "tax_year": 2023,
        "assessed_value": 180323,
        "market_value": 196391,
        "land_value": 12497,
        "improvement_value": 167826,
        "land_value_percentage": 6.9,
        "improvement_value_percentage": 93.1,
        "market_to_assessed_ratio": 1.09,
        "assessed_value_change": 1785,
        "assessed_value_change_pct": 1.0,
        "total_exemption_amount": 18000,
        "net_assessed_value": 162323,
        "assessment_date": "2023-01-15"
      },
      {
        "tax_year": 2022,
        "assessed_value": 178538,
        "market_value": 194447,
        "land_value": 12373,
        "improvement_value": 166165,
        "land_value_percentage": 6.9,
        "improvement_value_percentage": 93.1,
        "market_to_assessed_ratio": 1.09,
        "assessed_value_change": 0,
        "assessed_value_change_pct": 0.0,
        "total_exemption_amount": 18000,
        "net_assessed_value": 160538,
        "assessment_date": "2022-01-15"
      },
      {
        "tax_year": 2021,
        "assessed_value": 178538,
        "market_value": 194447,
        "land_value": 12373,
        "improvement_value": 166165,
        "land_value_percentage": 6.9,
        "improvement_value_percentage": 93.1,
        "market_to_assessed_ratio": 1.09,
        "assessed_value_change": 0,
        "assessed_value_change_pct": 0,
        "total_exemption_amount": 18000,
        "net_assessed_value": 160538,
        "assessment_date": "2021-01-15"
      }
    ]
  },
  "exemptions": {
    "parcel_id": "0933S00064000000",
    "exemptions": [
      {
        "tax_year": 2026,
        "total_exemption_amount": 18000,
        "total_exemption_count": 1,
        "homestead_exemption_amount": 18000,
        "senior_exemption_amount": 0,
        "veteran_exemption_amount": 0,
        "disability_exemption_amount": 0,
        "homestead_count": 1,
        "senior_count": 0,
        "veteran_count": 0,
        "disability_count": 0,
        "active_exemptions": 1,
        "pending_exemptions": 0,
        "expired_exemptions": 0,
        "exemption_types": "HOMESTEAD"
      },
      {
        "tax_year": 2025,
        "total_exemption_amount": 18000,
        "total_exemption_count": 1,
        "homestead_exemption_amount": 18000,
        "senior_exemption_amount": 0,
        "veteran_exemption_amount": 0,
        "disability_exemption_amount": 0,
        "homestead_count": 1,
        "senior_count": 0,
        "veteran_count": 0,
        "disability_count": 0,
        "active_exemptions": 1,
        "pending_exemptions": 0,
        "expired_exemptions": 0,
        "exemption_types": "HOMESTEAD"
      },
      {
        "tax_year": 2024,
        "total_exemption_amount": 18000,
        "total_exemption_count": 1,
        "homestead_exemption_amount": 18000,
        "senior_exemption_amount": 0,
        "veteran_exemption_amount": 0,
        "disability_exemption_amount": 0,
        "homestead_count": 1,
        "senior_count": 0,
        "veteran_count": 0,
        "disability_count": 0,
        "active_exemptions": 1,
        "pending_exemptions": 0,
        "expired_exemptions": 0,
        "exemption_types": "HOMESTEAD"
      }
    ]
  },
  "appeals": {
    "parcel_id": "0933S00064000000",
    "summary": {},
    "appeals": []
  },
  "comparables": {
    "parcel_id": "0933S00064000000",
    "comparables": []
  }
}