{
  "parcel": {
    "parcel_id": "1128D00064000000",
    "address": "331 CONROY ST",
    "city": "Elizabeth Twp",
    "zip_code": "15018",
    "county": "Allegheny",
    "current_owner_name": "331   CONROY ST",
    "current_mailing_address": "331   CONROY ST",
    "current_ownership_type": "REGULAR",
    "land_use_code": null,
    "land_use_description": "SINGLE FAMILY",
    "acreage": 0.331,
    "latitude": 40.4469,
    "longitude": -80.20084
  },
  "assessments": {
    "parcel_id": "1128D00064000000",
    "assessments": [
      {
        "tax_year": 2026,
        "assessed_value": 52700,
        "market_value": 52700,
        "land_value": 14900,
        "improvement_value": 37800,
        "land_value_percentage": 28.3,
        "improvement_value_percentage": 71.7,
        "market_to_assessed_ratio": 1.0,
        "assessed_value_change": 835,
        "assessed_value_change_pct": 1.61,
        "total_exemption_amount": 0,
        "net_assessed_value": 52700,
        "assessment_date": "2026-01-15"
      },
      {
        "tax_year": 2025,
        "assessed_value": 51865,
        "market_value": 51865,
        "land_value": 14663,
        "improvement_value": 37202,
        "land_value_percentage": 28.3,
        "improvement_value_percentage": 71.7,
        "market_to_assessed_ratio": 1.0,
        "assessed_value_change": -524,
        "assessed_value_change_pct": -1.0,
        "total_exemption_amount": 0,
        "net_assessed_value": 51865,
        "assessment_date": "2025-01-15"
      },
      {
        "tax_year": 2024,
        "assessed_value": 52389,
        "market_value": 52389,
        "land_value": 14812,
        "improvement_value": 37577,
        "land_value_percentage": 28.3,
        "improvement_value_percentage": 71.7,
        "market_to_assessed_ratio": 1.0,
        "assessed_value_change": 2494,
        "assessed_value_change_pct": 5.0,
        "total_exemption_amount": 0,
        "net_assessed_value": 52389,
        "assessment_date": "2024-01-15"
      },
      {
        "tax_year": 2023,
        "assessed_value": 49895,
        "market_value": 49895,
        "land_value": 14106,
        "improvement_value": 35789,
        "land_value_percentage": 28.3,
        "improvement_value_percentage": 71.7,
        "market_to_assessed_ratio": 1.0,
        "assessed_value_change": 1919,
        "assessed_value_change_pct": 4.0,
        "total_exemption_amount": 0,
        "net_assessed_value": 49895,
        "assessment_date": "2023-01-15"
      },
      {
        "tax_year": 2022,
        "assessed_value": 47976,
        "market_value": 47976,
        "land_value": 13564,
        "improvement_value": 34412,
        "land_value_percentage": 28.3,
        "improvement_value_percentage": 71.7,
        "market_to_assessed_ratio": 1.0,
        "assessed_value_change": 1397,
        "assessed_value_change_pct": 3.0,
        "total_exemption_amount": 0,
        "net_assessed_value": 47976,
        "assessment_date": "2022-01-15"
      },
      {
        "tax_year": 2021,
        "assessed_value": 46579,
        "market_value": 46579,
        "land_value": 13169,
        "improvement_value": 33410,
        "land_value_percentage": 28.3,
        "improvement_value_percentage": 71.7,
        "market_to_assessed_ratio": 1.0,
        "assessed_value_change": 0,
        "assessed_value_change_pct": 0,
        "total_exemption_amount": 0,
        "net_assessed_value": 46579,
        "assessment_date": "2021-01-15"
      }
    ]
  },
  "exemptions": {
    "parcel_id": "1128D00064000000",
    "exemptions": []
  },
  "appeals": {
    "parcel_id": "1128D00064000000",
    "summary": {},
    "appeals": []
  },
  "comparables": {
    "parcel_id": "1128D00064000000",
    "comparables": [
      {
        "parcel_id": "0553N00072000000",
        "address": "6526 SMITHFIELD ST",
        "city": "Elizabeth Twp",
        "zip_code": "15135",
        "current_owner_name": "6526   SMITHFIELD ST",
        "land_use_description": "SINGLE FAMILY",
        "acreage": null,
        "assessed_value": 52600,
        "market_value": 70600,
        "assessed_value_change_pct": -1.5,
        "distance_miles": 0.1
      },
      {
        "parcel_id": "0553S00172000000",
        "address": "1108 E SMITHFIELD ST",
        "city": "Elizabeth Twp",
        "zip_code": "15135",
        "current_owner_name": "1108  E SMITHFIELD ST",
        "land_use_description": "SINGLE FAMILY",
        "acreage": null,
        "assessed_value": 52900,
        "market_value": 70900,
        "assessed_value_change_pct": -0.3,
        "distance_miles": 0.3
      },
      {
        "parcel_id": "1128D00126000000",
        "address": "2741 FIRE STATION ST",
        "city": "Elizabeth Twp",
        "zip_code": "15018",
        "current_owner_name": "888   LOWBER RD",
        "land_use_description": "SINGLE FAMILY",
        "acreage": null,
        "assessed_value": 52400,
        "market_value": 52400,
        "assessed_value_change_pct": -3.7,
        "distance_miles": 0.5
      },
      {
        "parcel_id": "1569L00239000000",
        "address": "2121 DOUGLAS RUN RD",
        "city": "Elizabeth Twp",
        "zip_code": "15083",
        "current_owner_name": "1693  E ROY FURMAN HIGHWAY",
        "land_use_description": "SINGLE FAMILY",
        "acreage": null,
        "assessed_value": 52400,
        "market_value": 52400,
        "assessed_value_change_pct": 0.7,
        "distance_miles": 0.7
      },
      {
        "parcel_id": "0553N00301000000",
        "address": "2411 CANTERBURY DR",
        "city": "Elizabeth Twp",
        "zip_code": "15135",
        "current_owner_name": "2411   CANTERBURY DR",
        "land_use_description": "SINGLE FAMILY",
        "acreage": null,
        "assessed_value": 53200,
        "market_value": 71200,
        "assessed_value_change_pct": -2.5,
        "distance_miles": 0.9
      },
      {
        "parcel_id": "0554S00077000000",
        "address": "6509 SMITHFIELD ST",
        "city": "Elizabeth Twp",
        "zip_code": "15135",
        "current_owner_name": "6509   SMITHFIELD ST",
        "land_use_description": "SINGLE FAMILY",
        "acreage": null,
        "assessed_value": 52200,
        "market_value": 70200,
        "assessed_value_change_pct": 0.7,
        "distance_miles": 1.1
      }
    ]
  }
}